httpservermock/__init__.py
httpservermock/_version.py
httpservermock/py.typed
httpservermock-0.1.0.dist-info/LICENSE
httpservermock-0.1.0.dist-info/WHEEL
httpservermock-0.1.0.dist-info/METADATA
httpservermock-0.1.0.dist-info/RECORD
