Metadata-Version: 2.1
Name: httpservermock
Version: 0.1.0
Summary: A python library that provides a http server mock that can be used for testing code that should interact with an http server
License: MIT-0
Requires-Python: >=3.6.2,<4.0.0
Classifier: License :: Other/Proprietary License
Classifier: Programming Language :: Python :: 3
Classifier: Programming Language :: Python :: 3.10
Classifier: Programming Language :: Python :: 3.7
Classifier: Programming Language :: Python :: 3.8
Classifier: Programming Language :: Python :: 3.9
